nanbi/__init__.py
nanbi/adapters/__init__.py
nanbi/adapters/column.py
nanbi/adapters/dataframe.py
nanbi/connectors/__init__.py
nanbi/connectors/common.py
nanbi/connectors/pandas.py
nanbi/evaluators/__init__.py
nanbi/evaluators/base.py
nanbi/evaluators/pandas.py
nanbi/operations/__init__.py
nanbi/operations/auxiliary.py
nanbi/operations/base.py
nanbi/operations/leaf.py
nanbi/operations/node.py
nanbi-0.0.1.dist-info/LICENSE
nanbi-0.0.1.dist-info/METADATA
nanbi-0.0.1.dist-info/WHEEL
nanbi-0.0.1.dist-info/top_level.txt
nanbi-0.0.1.dist-info/RECORD
