Metadata-Version: 2.1
Name: nanbi
Version: 0.0.1
Summary: A framework that allows the definition of data transformations in a composable way, agnostic of data processing engine.
Author-email: Eduardo Emery <emeryecs@gmail.com>
License: MIT License
Project-URL: Homepage, https://github.com/EEmery/nanbi-python
Keywords: data,transformation,pandas,SQL,Spark
Classifier: License :: OSI Approved :: MIT License
Classifier: Programming Language :: Python
Classifier: Programming Language :: Python :: 3
Requires-Python: >=3.8
License-File: LICENSE
Requires-Dist: pandas (==1.5.2)
Provides-Extra: dev
Requires-Dist: coverage (==7.0.1) ; extra == 'dev'
Requires-Dist: pyflakes (==3.0.1) ; extra == 'dev'
Requires-Dist: black (==22.12.0) ; extra == 'dev'
